{
  "name": "Registro Comentários Outbound Instagram",
  "nodes": [
    {
      "parameters": {
        "httpMethod": "POST",
        "path": "outbound-comment",
        "responseMode": "responseNode",
        "options": {}
      },
      "id": "webhook-trigger",
      "name": "Webhook Trigger",
      "type": "n8n-nodes-base.webhook",
      "typeVersion": 2,
      "position": [250, 300],
      "webhookId": "outbound-comment-webhook"
    },
    {
      "parameters": {
        "method": "POST",
        "url": "https://gliigkupoebmlbwyvijp.supabase.co/functions/v1/n8n-comment-webhook",
        "sendHeaders": true,
        "headerParameters": {
          "parameters": [
            {
              "name": "Content-Type",
              "value": "application/json"
            },
            {
              "name": "Authorization",
              "value": "Bearer eyJhbGciOiJIUzI1NiIsInR5cCI6IkpXVCJ9.eyJpc3MiOiJzdXBhYmFzZSIsInJlZiI6ImdsaWlna3Vwb2VibWxid3l2aWpwIiwicm9sZSI6ImFub24iLCJpYXQiOjE3NjYwMDAxNDcsImV4cCI6MjA4MTU3NjE0N30.HnhqYYFjW9DjFUsUkrZDuCShCOU2P73o_DqvkVyVr38"
            }
          ]
        },
        "sendBody": true,
        "specifyBody": "json",
        "jsonBody": "={\n  \"action\": \"register_outbound\",\n  \"account_id\": \"{{ $json.account_id }}\",\n  \"account_name\": \"{{ $json.account_name }}\",\n  \"target_username\": \"{{ $json.target_username }}\",\n  \"comment_text\": \"{{ $json.comment_text }}\",\n  \"post_url\": \"{{ $json.post_url || '' }}\"\n}",
        "options": {}
      },
      "id": "http-request",
      "name": "Enviar para Edge Function",
      "type": "n8n-nodes-base.httpRequest",
      "typeVersion": 4.2,
      "position": [500, 300]
    },
    {
      "parameters": {
        "respondWith": "json",
        "responseBody": "={{ $json }}",
        "options": {}
      },
      "id": "response-node",
      "name": "Resposta Webhook",
      "type": "n8n-nodes-base.respondToWebhook",
      "typeVersion": 1.1,
      "position": [750, 300]
    }
  ],
  "connections": {
    "Webhook Trigger": {
      "main": [
        [
          {
            "node": "Enviar para Edge Function",
            "type": "main",
            "index": 0
          }
        ]
      ]
    },
    "Enviar para Edge Function": {
      "main": [
        [
          {
            "node": "Resposta Webhook",
            "type": "main",
            "index": 0
          }
        ]
      ]
    }
  },
  "pinData": {},
  "settings": {
    "executionOrder": "v1"
  },
  "staticData": null,
  "tags": [],
  "triggerCount": 0
}
